cli/__init__.py
cli/cli.py
cli/console.py
cli/script.py
djang_setup-0.0.6.dist-info/LICENSE
djang_setup-0.0.6.dist-info/METADATA
djang_setup-0.0.6.dist-info/WHEEL
djang_setup-0.0.6.dist-info/entry_points.txt
djang_setup-0.0.6.dist-info/top_level.txt
djang_setup-0.0.6.dist-info/RECORD
