Metadata-Version: 2.1
Name: djang-setup
Version: 0.0.6
Summary: A CLI tool to set up Django projects for you
Home-page: https://github.com/fulanii/djnago_setup
Author: Yassine
Author-email: Yassine <yassine@yassinecodes.dev>
License: MIT
Project-URL: Homepage, https://github.com/fulanii/django_setup
Classifier: Programming Language :: Python :: 3
Classifier: Framework :: Django
Classifier: License :: OSI Approved :: MIT License
Classifier: Operating System :: OS Independent
Requires-Python: >=3.6
License-File: LICENSE
Requires-Dist: astor==0.8.1
Requires-Dist: black==24.10.0
Requires-Dist: click==8.1.8
Requires-Dist: rich==13.9.4
Requires-Dist: django-environ==0.11.2
